pytest_choose/__init__.py
pytest_choose/analysis.py
pytest_choose/filter.py
pytest_choose/plugin.py
pytest_choose/terminal_io.py
test/__init__.py
test/main.py
test/cases/__init__.py
test/cases/conftest.py
test/cases/test_choose.py
pytest_choose-0.2.0.dist-info/LICENSE
pytest_choose-0.2.0.dist-info/METADATA
pytest_choose-0.2.0.dist-info/WHEEL
pytest_choose-0.2.0.dist-info/entry_points.txt
pytest_choose-0.2.0.dist-info/top_level.txt
pytest_choose-0.2.0.dist-info/RECORD
