Metadata-Version: 2.1
Name: pytest-choose
Version: 0.2.0
Summary: Provide the pytest with the ability to collect use cases based on rules in text files
Home-page: https://github.com/NaoOtosaka/pytest-choose
Author: Azusa
Author-email: naotosaka@126.com
License: GPLv3
Project-URL: Source Code, https://github.com/NaoOtosaka/pytest-choose
Project-URL: Bug Tracker, https://github.com/NaoOtosaka/pytest-choose/issues
Keywords: pytest
Classifier: Framework :: Pytest
Classifier: Intended Audience :: Developers
Classifier: Topic :: Software Development :: Quality Assurance
Classifier: Topic :: Software Development :: Testing
Classifier: Programming Language :: Python :: 3
Classifier: Programming Language :: Python :: 3 :: Only
Classifier: Programming Language :: Python :: 3.9
Classifier: Programming Language :: Python :: 3.10
Classifier: Programming Language :: Python :: 3.11
Classifier: License :: OSI Approved :: GNU General Public License v3 (GPLv3)
Classifier: Operating System :: OS Independent
License-File: LICENSE
Requires-Dist: pytest >=7.0.0
